tranzlate/__init__.py
tranzlate/exceptions.py
tranzlate/translator.py
tranzlate-1.0.0.dist-info/LICENSE
tranzlate-1.0.0.dist-info/METADATA
tranzlate-1.0.0.dist-info/WHEEL
tranzlate-1.0.0.dist-info/top_level.txt
tranzlate-1.0.0.dist-info/RECORD
