Metadata-Version: 2.1
Name: tranzlate
Version: 1.0.0
Summary: Translate text, files, markup and BeautifulSoup.
Author-email: ti-oluwa <tioluwa.dev@gmail.com>
Maintainer-email: ti-oluwa <tioluwa.dev@gmail.com>
Project-URL: Homepage, https://github.com/ti-oluwa/tranzlate
Project-URL: Bug Tracker, https://github.com/ti-oluwa/tranzlate/issues
Project-URL: Repository, https://github.com/ti-oluwa/tranzlate
Keywords: translate,translation,google translate,bing translate,translate text,translate files,translate markup,translate html,translate xml,beautifulsoup4,detect language
Classifier: Programming Language :: Python :: 3
Classifier: License :: OSI Approved :: MIT License
Classifier: Operating System :: OS Independent
Classifier: Development Status :: 5 - Production/Stable
Classifier: Intended Audience :: Developers
Classifier: Natural Language :: English
Classifier: Typing :: Typed
Requires-Python: >=3.7
License-File: LICENSE
Requires-Dist: translators ==5.8.9
Requires-Dist: simple-file-handler >=0.0.1
Requires-Dist: asgiref ==3.8.1
